dictionary/__init__.py
dictionary/dictionary.py
CS453_HW1_Dogukan-3.0.0.dist-info/METADATA
CS453_HW1_Dogukan-3.0.0.dist-info/WHEEL
CS453_HW1_Dogukan-3.0.0.dist-info/top_level.txt
CS453_HW1_Dogukan-3.0.0.dist-info/RECORD
