Metadata-Version: 2.1
Name: CS453-HW1-Dogukan
Version: 3.0.0
Summary: UNKNOWN
Author: Doğukan Ertunga Kurnaz
License: UNKNOWN
Platform: UNKNOWN
Requires-Python: >=3.8
Requires-Dist: requests (>=2.23.0)
